arcade_twilio/__init__.py
arcade_twilio/tools/__init__.py
arcade_twilio/tools/config.py
arcade_twilio/tools/send_sms.py
arcade_twilio/tools/send_twilio_message.py
arcade_twilio/tools/send_whatsapp.py
arcade_twilio-0.1.0.dist-info/LICENCE
arcade_twilio-0.1.0.dist-info/METADATA
arcade_twilio-0.1.0.dist-info/WHEEL
arcade_twilio-0.1.0.dist-info/RECORD
